spyder_remote_services/__init__.py
spyder_remote_services/__main__.py
spyder_remote_services/app.py
spyder_remote_services/utils.py
spyder_remote_services/services/__init__.py
spyder_remote_services/services/environ/__init__.py
spyder_remote_services/services/environ/handler.py
spyder_remote_services/services/files/__init__.py
spyder_remote_services/services/files/base.py
spyder_remote_services/services/files/compression.py
spyder_remote_services/services/files/handlers.py
spyder_remote_services/services/spyder_kernels/__init__.py
spyder_remote_services/services/spyder_kernels/patches.py
spyder_remote_services/services/spyder_kernels/provisioner.py
spyder_remote_services-1.0.0.data/data/etc/jupyter/jupyter_server_config.d/spyder_remote_services.json
spyder_remote_services-1.0.0.dist-info/METADATA
spyder_remote_services-1.0.0.dist-info/WHEEL
spyder_remote_services-1.0.0.dist-info/entry_points.txt
spyder_remote_services-1.0.0.dist-info/licenses/AUTHORS.txt
spyder_remote_services-1.0.0.dist-info/licenses/LICENSE.txt
spyder_remote_services-1.0.0.dist-info/RECORD
